doctran_openai/__init__.py
doctran_openai/doctran_openai.py
doctran_openai/transformers/__init__.py
doctran_openai/transformers/transformers.py
doctran_openai-0.0.31.dist-info/LICENSE
doctran_openai-0.0.31.dist-info/METADATA
doctran_openai-0.0.31.dist-info/WHEEL
doctran_openai-0.0.31.dist-info/RECORD
