Metadata-Version: 2.1
Name: doctran_openai
Version: 0.0.31
Summary: Document transformation framework for vector based retrieval
Author: William Yang
Author-email: yangfei86@gmail.com
Requires-Python: >=3.10.0,<4.0.0
Classifier: Programming Language :: Python :: 3
Classifier: Programming Language :: Python :: 3.10
Classifier: Programming Language :: Python :: 3.11
Classifier: Programming Language :: Python :: 3.12
Requires-Dist: lxml (>=4.9.4,<5.0.0)
Requires-Dist: openai (>=1.37.2,<2.0.0)
Requires-Dist: presidio-analyzer (>=2.2.355,<3.0.0)
Requires-Dist: presidio-anonymizer (>=2.2.355,<3.0.0)
Requires-Dist: pydantic (>=2.8.2,<3.0.0)
Requires-Dist: spacy (>=3.7.5,<4.0.0)
Requires-Dist: tiktoken (>=0.7.0,<0.8.0)
